apache_replay/__init__.py
apache_replay/parser.py
apache_replay/player.py
apache_replay/script.py
apache_replay-0.0.3.dist-info/METADATA
apache_replay-0.0.3.dist-info/WHEEL
apache_replay-0.0.3.dist-info/entry_points.txt
apache_replay-0.0.3.dist-info/top_level.txt
apache_replay-0.0.3.dist-info/RECORD
