Metadata-Version: 2.1
Name: apache-replay
Version: 0.0.3
Summary: Facilitates replaying of Apache files in Common Log and Combined Log format
Home-page: https://github.com/danizen/apache-replay.git
Author: Daniel Davis
Author-email: dan@danizen.net
License: UNKNOWN
Platform: UNKNOWN
Classifier: Development Status :: 3 - Alpha
Classifier: Programming Language :: Python :: 3
Classifier: License :: OSI Approved :: MIT License
Classifier: Operating System :: OS Independent
Classifier: Environment :: Console
Classifier: Intended Audience :: Developers
Classifier: Intended Audience :: System Administrators
Classifier: Topic :: Software Development :: Testing :: Traffic Generation
Requires-Dist: attrs
Requires-Dist: requests
